nofeardb/__init__.py
nofeardb/datatypes.py
nofeardb/engine.py
nofeardb/enums.py
nofeardb/exceptions.py
nofeardb/expr.py
nofeardb/orm.py
nofeardb/query.py
NofearDB-1.0.0.dist-info/LICENSE
NofearDB-1.0.0.dist-info/METADATA
NofearDB-1.0.0.dist-info/WHEEL
NofearDB-1.0.0.dist-info/top_level.txt
NofearDB-1.0.0.dist-info/RECORD
