Metadata-Version: 2.1
Name: NofearDB
Version: 1.0.0
Summary: A small database management system package for an embedded NoSQL database which can be used by multiple hosts in parallel.
Author-email: Philipp Nitsche <philippnitsche.vfx@gmail.com>
Project-URL: Homepage, https://github.com/philipp-vfx/nofeardb
Project-URL: Issues, https://github.com/philipp-vfx/nofeardb/issues
Classifier: Programming Language :: Python :: 3
Classifier: License :: OSI Approved :: MIT License
Classifier: Operating System :: OS Independent
Requires-Python: >=3.6
License-File: LICENSE
